dji_drone_data/__init__.py
dji_drone_data/analyzer.py
dji_drone_data/parser.py
dji_drone_data-0.1.0.dist-info/METADATA
dji_drone_data-0.1.0.dist-info/WHEEL
dji_drone_data-0.1.0.dist-info/top_level.txt
dji_drone_data-0.1.0.dist-info/RECORD
